{
  "kind": "collectionType",
  "collectionName": "jobs",
  "info": {
    "singularName": "job",
    "pluralName": "jobs",
    "displayName": "Jobs",
    "description": ""
  },
  "options": {
    "draftAndPublish": true
  },
  "pluginOptions": {},
  "attributes": {
    "organization": {
      "type": "string",
      "maxLength": 100
    },
    "dateDeleted": {
      "type": "datetime"
    },
    "jobId": {
      "type": "uid",
      "required": true
    },
    "job": {
      "type": "json"
    },
    "jobUser": {
      "type": "relation",
      "relation": "manyToOne",
      "target": "api::job-user.job-user",
      "inversedBy": "jobs"
    },
    "location": {
      "type": "json"
    },
    "intro": {
      "type": "richtext"
    },
    "tasks": {
      "type": "richtext"
    },
    "offer": {
      "type": "richtext"
    },
    "jobTitle": {
      "type": "string"
    },
    "reference": {
      "type": "string"
    },
    "salary": {
      "type": "json"
    },
    "applyEmail": {
      "type": "email"
    },
    "applyUrl": {
      "type": "string"
    },
    "formattedAddress": {
      "type": "string"
    }
  }
}
